exomiser_ml/__init__.py
exomiser_ml/cli.py
exomiser_ml/main.py
exomiser_ml/data/create_features/__init__.py
exomiser_ml/data/create_features/add_features.py
exomiser_ml/data/create_features/calculate_acmg_ppp.py
exomiser_ml/data/create_features/get_causative_variant.py
exomiser_ml/data/split_data/__init__.py
exomiser_ml/data/split_data/split_train_and_test.py
exomiser_ml/models/__init__.py
exomiser_ml/models/classifier_models.py
exomiser_ml/models/generalised_additive_model.py
exomiser_ml/models/logistic_regression_manual_sigmoid_calculation.py
exomiser_ml/post_process/__init__.py
exomiser_ml/post_process/post_process.py
exomiser_ml/utils/__init__.py
exomiser_ml/utils/write_metadata.py
exomiser_ml-0.1.17.dist-info/METADATA
exomiser_ml-0.1.17.dist-info/WHEEL
exomiser_ml-0.1.17.dist-info/entry_points.txt
exomiser_ml-0.1.17.dist-info/top_level.txt
exomiser_ml-0.1.17.dist-info/RECORD
