Metadata-Version: 2.4
Name: exomiser-ml
Version: 0.1.17
Summary: A machine learning pipeline for variant prioritisation using Exomiser output.
Author-email: Yasemin Bridges <y.bridges@qmul.ac.uk>
Requires-Python: >=3.12
Requires-Dist: interpret>=0.7.2
Requires-Dist: pheval>=0.5.4
Requires-Dist: shap>=0.47.2
Requires-Dist: xgboost>=3.0.0
